bou.py
bou-0.0.3.dist-info/LICENSE
bou-0.0.3.dist-info/METADATA
bou-0.0.3.dist-info/WHEEL
bou-0.0.3.dist-info/entry_points.txt
bou-0.0.3.dist-info/top_level.txt
bou-0.0.3.dist-info/RECORD
