Metadata-Version: 2.1
Name: bou
Version: 0.0.3
Summary: Simple YAML-driven build or task runner
Home-page: https://bou-project.org
Author: Raoul Snyman
Author-email: raoul@snyman.info
License: MIT
Keywords: build,task
Platform: UNKNOWN
Classifier: Development Status :: 3 - Alpha
Classifier: Intended Audience :: Developers
Classifier: License :: OSI Approved :: MIT License
Classifier: Operating System :: POSIX
Classifier: Programming Language :: Python :: 3
Classifier: Programming Language :: Python :: 3.7
Classifier: Programming Language :: Python :: 3.8
Classifier: Programming Language :: Python :: 3.9
Classifier: Programming Language :: Python :: 3.10
Classifier: Topic :: Utilities
Requires-Python: >=3.7
Requires-Dist: PyYAML
